Metadata-Version: 1.2
Name: apispec-py35-compat
Version: 1.0.0
Summary: Python 3.5 compat package for apispec
Home-page: https://github.com/theirix/apispec-py35-compat
Author: theirix
Author-email: theirix@gmail.com
License: MIT
Platform: UNKNOWN
Classifier: Development Status :: 3 - Alpha
Classifier: Intended Audience :: Developers
Classifier: License :: OSI Approved :: MIT License
Requires-Python: >=3.5, <4
